<annotation>
	<folder>jpg2</folder>
	<filename>00372.jpg</filename>
	<path>H:\p52\jpg2\00372.jpg</path>
	<source>
		<database>Unknown</database>
	</source>
	<size>
		<width>1920</width>
		<height>1080</height>
		<depth>3</depth>
	</size>
	<segmented>0</segmented>
	<object>
		<name>bulldozer</name>
		<pose>Unspecified</pose>
		<truncated>0</truncated>
		<difficult>0</difficult>
		<bndbox>
			<xmin>135</xmin>
			<ymin>191</ymin>
			<xmax>884</xmax>
			<ymax>745</ymax>
		</bndbox>
	</object>
	<object>
		<name>bulldozer</name>
		<pose>Unspecified</pose>
		<truncated>0</truncated>
		<difficult>0</difficult>
		<bndbox>
			<xmin>1118</xmin>
			<ymin>235</ymin>
			<xmax>1707</xmax>
			<ymax>783</ymax>
		</bndbox>
	</object>
</annotation>
